README.rst
setup.py
NAFFoLiAPy.egg-info/PKG-INFO
NAFFoLiAPy.egg-info/SOURCES.txt
NAFFoLiAPy.egg-info/dependency_links.txt
NAFFoLiAPy.egg-info/entry_points.txt
NAFFoLiAPy.egg-info/not-zip-safe
NAFFoLiAPy.egg-info/requires.txt
NAFFoLiAPy.egg-info/top_level.txt
naffoliapy/__init__.py
naffoliapy/folia2naf.py
naffoliapy/naf2folia.py
naffoliapy/../examples/100911_Northrop_Grumman_and_Airbus_parent_EADS_defeat_Boeing.folia.xml
naffoliapy/../examples/100911_Northrop_Grumman_and_Airbus_parent_EADS_defeat_Boeing.naf.xml
naffoliapy/../examples/nederlab-dpo.35.mpeg21.0300.alto.folia.corrected.folia.xml
naffoliapy/../examples/opencgn-fv601273.folia.xml
naffoliapy/../examples/potgrond.frog.folia.xml
naffoliapy/../examples/valkuil.folia.xml
naffoliapy/tests/__init__.py
naffoliapy/tests/naf2folia.py