Metadata-Version: 1.1
Name: NAFFoLiAPy
Version: 0.1.1
Summary: Converters between two formats for linguistic annotation: FoLiA and NAF
Home-page: https://github.com/cltl/NAFFoLiAPy
Author: Antske Fokkens and Maarten van Gompel
Author-email: proycon@anaproy.nl
License: GPL
Keywords: nlp computational_linguistics linguistics converter folia naf
Platform: UNKNOWN
Classifier: Development Status :: 4 - Beta
Classifier: Topic :: Text Processing :: Linguistic
Classifier: Programming Language :: Python :: 2.7
Classifier: Programming Language :: Python :: 3
Classifier: Operating System :: POSIX
Classifier: Intended Audience :: Developers
Classifier: Intended Audience :: Science/Research
Classifier: License :: OSI Approved :: GNU General Public License v3 (GPLv3)
